pubkeeper/protocol/v1/__init__.py
pubkeeper/protocol/v1/constant.py
pubkeeper/protocol/v1/frame.py
pubkeeper/protocol/v1/packet.py
pubkeeper/protocol/v1/protocol.py
pubkeeper.protocol.v1-1.1.1.dist-info/DESCRIPTION.rst
pubkeeper.protocol.v1-1.1.1.dist-info/METADATA
pubkeeper.protocol.v1-1.1.1.dist-info/RECORD
pubkeeper.protocol.v1-1.1.1.dist-info/WHEEL
pubkeeper.protocol.v1-1.1.1.dist-info/metadata.json
pubkeeper.protocol.v1-1.1.1.dist-info/top_level.txt
