Metadata-Version: 2.0
Name: pubkeeper.protocol.v1
Version: 1.1.1
Summary: Brew, Fill, Consume
Home-page: http://github.com/pubkeeper/python-protocol
Author: n.io
Author-email: info@n.io
License: UNKNOWN
Keywords: pubkeeper,python-protocol-v1
Platform: UNKNOWN
Classifier: License :: Other/Proprietary License
Classifier: Programming Language :: Python :: 3
Classifier: Programming Language :: Python :: 3.5
